LICENSE.txt
README.md
setup.py
HARPipe.egg-info/PKG-INFO
HARPipe.egg-info/SOURCES.txt
HARPipe.egg-info/dependency_links.txt
HARPipe.egg-info/requires.txt
HARPipe.egg-info/top_level.txt
harp/__init__.py
harp/harp_pipeline.py
harp/train_restoration.py
harp/core/__init__.py
harp/core/base_dataset.py
harp/core/base_model.py
harp/core/base_network.py
harp/core/logger.py
harp/core/praser.py
harp/core/util.py
harp/data/__init__.py
harp/data/dataset.py
harp/data/util/__init__.py
harp/data/util/auto_augment.py
harp/data/util/mask.py
harp/models/__init__.py
harp/models/loss.py
harp/models/metric.py
harp/models/model.py
harp/models/network.py
harp/models/guided_diffusion_modules/__init__.py
harp/models/guided_diffusion_modules/nn.py
harp/models/guided_diffusion_modules/unet.py
harp/pipeline/__init__.py
harp/pipeline/artifact_detection.py
harp/pipeline/artifact_ranking.py
harp/pipeline/artifact_restoration.py
harp/pipeline/artifact_segmentation.py
harp/pipeline/eval.py
harp/pipeline/harp_dataset.py
harp/pipeline/heatmap.py
harp/pipeline/parser.py