Metadata-Version: 2.1
Name: HARPipe
Version: 1.1.2
Summary: Histological Artifact Restoration Pipeline
Home-page: https://github.com/MECLabTUDA/HARP
Author: MECLabTUDa
Author-email: moritz.fuchs@gris.tu-darmstadt.de
Classifier: Programming Language :: Python :: 3
Classifier: License :: OSI Approved
Classifier: Operating System :: OS Independent
Requires-Python: >=3.11.0
License-File: LICENSE.txt
